elasticlogger/__init__.py
elasticlogger/base_logger.py
elasticlogger/errors.py
elasticlogger/hooks/__init__.py
elasticlogger/hooks/elasticsearch/__init__.py
elasticlogger/hooks/elasticsearch/elasticsearch.py
elasticlogger/hooks/elasticsearch/errors.py
elasticlogger/hooks/hook_context.py
elasticlogger/hooks/hooks.py
elasticlogger/logger.py
elasticlogger/ports/__init__.py
elasticlogger/ports/elasticsearch/__init__.py
elasticlogger/ports/elasticsearch/elasticsearch.py
elasticlogger/types/__init__.py
elasticlogger/types/context.py
elasticlogger/types/json_encoder.py
elasticlogger/types/linked_list.py
elasticlogger/utils/__init__.py
elasticlogger/utils/utils.py
elasticlogger-2.4.0.dist-info/LICENSE
elasticlogger-2.4.0.dist-info/WHEEL
elasticlogger-2.4.0.dist-info/METADATA
elasticlogger-2.4.0.dist-info/RECORD
